clanker/__init__.py
clanker/__main__.py
clanker/cli.py
clanker/config.py
clanker/llm.py
clanker/paste.py
clanker-1.0.0.dist-info/METADATA
clanker-1.0.0.dist-info/WHEEL
clanker-1.0.0.dist-info/entry_points.txt
clanker-1.0.0.dist-info/licenses/LICENSE
clanker-1.0.0.dist-info/RECORD
