Metadata-Version: 2.4
Name: clanker
Version: 1.0.0
Summary: LLM shell helper that pastes commands into your terminal
Project-URL: Homepage, https://github.com/redtachyon/clanker
Project-URL: Repository, https://github.com/redtachyon/clanker
Project-URL: Issues, https://github.com/redtachyon/clanker/issues
Author-email: Ariel Kwiatkowski <ariel.j.kwiatkowski@gmail.com>
License: MIT License
License-File: LICENSE
Keywords: assistant,cli,llm,shell
Classifier: Development Status :: 3 - Alpha
Classifier: Environment :: Console
Classifier: Intended Audience :: Developers
Classifier: License :: OSI Approved :: MIT License
Classifier: Programming Language :: Python :: 3
Classifier: Programming Language :: Python :: 3 :: Only
Classifier: Topic :: Utilities
Requires-Python: >=3.11
